heliosat/__init__.py
heliosat/caching.py
heliosat/datafile.py
heliosat/smoothing.py
heliosat/spacecraft.py
heliosat/spice.py
heliosat/transform.py
heliosat/util.py
heliosat/spacecraft/bepi.json
heliosat/spacecraft/dscovr.json
heliosat/spacecraft/kernels.json
heliosat/spacecraft/manager.json
heliosat/spacecraft/psp.json
heliosat/spacecraft/solo.json
heliosat/spacecraft/stereo.json
heliosat/spacecraft/wind.json
HelioSat-0.6.2.dist-info/LICENSE
HelioSat-0.6.2.dist-info/METADATA
HelioSat-0.6.2.dist-info/WHEEL
HelioSat-0.6.2.dist-info/top_level.txt
HelioSat-0.6.2.dist-info/RECORD
