Metadata-Version: 2.1
Name: HelioSat
Version: 0.6.2
Summary: UNKNOWN
Home-page: https://github.com/ajefweiss/HelioSat
Author: Andreas J. Weiss
Author-email: andreas.weiss@oeaw.ac.at
License: UNKNOWN
Keywords: astrophysics,solar physics,space weather
Platform: UNKNOWN
Classifier: Development Status :: 4 - Beta
Classifier: Intended Audience :: Science/Research
Classifier: License :: OSI Approved :: MIT License
Classifier: Operating System :: OS Independent
Classifier: Programming Language :: Python :: 3
Classifier: Programming Language :: Python :: 3.9
Classifier: Topic :: Scientific/Engineering
Classifier: Topic :: Scientific/Engineering :: Physics
Requires-Dist: bs4
Requires-Dist: cdflib (>=0.3.19)
Requires-Dist: netcdf4
Requires-Dist: numba
Requires-Dist: numpy
Requires-Dist: requests
Requires-Dist: requests-ftp
Requires-Dist: spiceypy
